fastapi_di_viz/__init__.py
fastapi_di_viz/app.py
fastapi_di_viz/py.typed
fastapi_di_viz/sample/app.py
fastapi_di_viz/utils.py
fastapi_di_viz-0.2.0.dist-info/METADATA
fastapi_di_viz-0.2.0.dist-info/WHEEL
fastapi_di_viz-0.2.0.dist-info/entry_points.txt
fastapi_di_viz-0.2.0.dist-info/RECORD
